{
  "project_info": {
    "project_number": "1073348339060",
    "project_id": "acheiimoveis-7f18d",
    "storage_bucket": "acheiimoveis-7f18d.appspot.com"
  },
  "client": [
    {
      "client_info": {
        "mobilesdk_app_id": "1:1073348339060:android:11a6b1b2452ed5d5433821",
        "android_client_info": {
          "package_name": "com.TeionGames.TesteMRV"
        }
      },
      "oauth_client": [
        {
          "client_id": "1073348339060-ffc25al6jpstmava09eib1keliob9dnb.apps.googleusercontent.com",
          "client_type": 3
        }
      ],
      "api_key": [
        {
          "current_key": "AIzaSyDLL0RCyH92tDfBMuRoSghMRGPV-67ov3Q"
        }
      ],
      "services": {
        "appinvite_service": {
          "other_platform_oauth_client": [
            {
              "client_id": "1073348339060-ffc25al6jpstmava09eib1keliob9dnb.apps.googleusercontent.com",
              "client_type": 3
            }
          ]
        }
      }
    }
  ],
  "configuration_version": "1"
}